setup.py
aljp_messagemedia_rest_api.egg-info/PKG-INFO
aljp_messagemedia_rest_api.egg-info/SOURCES.txt
aljp_messagemedia_rest_api.egg-info/dependency_links.txt
aljp_messagemedia_rest_api.egg-info/requires.txt
aljp_messagemedia_rest_api.egg-info/top_level.txt
messagemedia_rest_api/__init__.py
messagemedia_rest_api/api_client.py
messagemedia_rest_api/configuration.py
messagemedia_rest_api/rest.py
messagemedia_rest_api/apis/__init__.py
messagemedia_rest_api/apis/delivery_reports_api.py
messagemedia_rest_api/apis/messaging_api.py
messagemedia_rest_api/apis/messaging_reports_api.py
messagemedia_rest_api/apis/replies_api.py
messagemedia_rest_api/models/__init__.py
messagemedia_rest_api/models/accounts_body.py
messagemedia_rest_api/models/action_body.py
messagemedia_rest_api/models/async_delivery_report_detail_request.py
messagemedia_rest_api/models/async_delivery_reports_summary_request.py
messagemedia_rest_api/models/async_delivery_sent_messages_request.py
messagemedia_rest_api/models/async_received_messages_detail_request.py
messagemedia_rest_api/models/async_received_messages_summary_request.py
messagemedia_rest_api/models/async_report.py
messagemedia_rest_api/models/async_report_response.py
messagemedia_rest_api/models/async_sent_messages_detail_request.py
messagemedia_rest_api/models/delivery_options_body.py
messagemedia_rest_api/models/delivery_options_body_inner.py
messagemedia_rest_api/models/delivery_report.py
messagemedia_rest_api/models/delivery_report_body.py
messagemedia_rest_api/models/delivery_report_id.py
messagemedia_rest_api/models/delivery_reports.py
messagemedia_rest_api/models/destination_address_body.py
messagemedia_rest_api/models/destination_address_country_body.py
messagemedia_rest_api/models/end_date_body.py
messagemedia_rest_api/models/inline_response_200.py
messagemedia_rest_api/models/inline_response_400.py
messagemedia_rest_api/models/message_format_body.py
messagemedia_rest_api/models/message_status_code.py
messagemedia_rest_api/models/messages.py
messagemedia_rest_api/models/metadata_key_body.py
messagemedia_rest_api/models/metadata_keys_response.py
messagemedia_rest_api/models/metadata_keys_response_properties.py
messagemedia_rest_api/models/metadata_value_body.py
