Metadata-Version: 1.0
Name: aljp-messagemedia-rest-api
Version: 1.0.0
Summary: MessageMedia REST API
Home-page: https://www.messagemedia.com/contact-us
Author: UNKNOWN
Author-email: support@messagemedia.com
License: UNKNOWN
Platform: UNKNOWN
